cdl.cpython-310-aarch64-linux-gnu.so
condorcet_domain-1.3.2.dist-info/RECORD
condorcet_domain-1.3.2.dist-info/METADATA
condorcet_domain-1.3.2.dist-info/WHEEL
condorcet_domain-1.3.2.dist-info/licenses/license
