Metadata-Version: 2.1
Name: condorcet-domain
Version: 1.3.2
Summary: CDL: A fast and flexible library for the study of permutation sets with structural restrictions
Author-Email: Dr Bei Zhou <bei.zhou@imperial.ac.uk>
License:                                  Apache License
Project-URL: Documentation, https://arxiv.org/pdf/2309.06306
Project-URL: Repository, https://github.com/sagebei/cdl
Requires-Python: >=3.8
